json_any/__init__.py
json_any/json_to_object.py
json_any/object_to_json.py
json_any/version.py
json_any/api/compression.py
json_any/api/storage.py
json_any/api/type.py
json_any/catalog/module.py
json_any/catalog/registration.py
json_any/catalog/type.py
json_any/constant/compression.py
json_any/constant/json.py
json_any/constant/python.py
json_any/constant/module/matplotlib.py
json_any/constant/module/networkx.py
json_any/constant/module/numpy.py
json_any/constant/module/pandas.py
json_any/constant/module/scipy.py
json_any/constant/module/xarray.py
json_any/extension/module.py
json_any/extension/type.py
json_any/extension/module_/numpy.py
json_any/extension/module_/pandas.py
json_any/task/compression.py
json_any/task/storage.py
json_any/type/error.py
json_any-2024.8.dist-info/METADATA
json_any-2024.8.dist-info/WHEEL
json_any-2024.8.dist-info/top_level.txt
json_any-2024.8.dist-info/RECORD
