Metadata-Version: 2.1
Name: json-any
Version: 2024.8
Summary: JSON and unJSON objects of any type
Home-page: https://src.koda.cnrs.fr/eric.debreuve/json-any/
Author: Eric Debreuve
Author-email: eric.debreuve@cnrs.fr
License: CeCILL-2.1
Project-URL: Documentation, https://src.koda.cnrs.fr/eric.debreuve/json-any/-/wikis/home
Project-URL: Source, https://src.koda.cnrs.fr/eric.debreuve/json-any/
Keywords: json,library
Classifier: Topic :: Software Development
Classifier: Intended Audience :: Developers
Classifier: License :: OSI Approved :: CEA CNRS Inria Logiciel Libre License, version 2.1 (CeCILL-2.1)
Classifier: Programming Language :: Python :: 3
Classifier: Development Status :: 5 - Production/Stable
Requires-Python: >=3.11
